{
    "asset": {
        "format": "jpg",
        "id": "e6fd0919ade0603d62ca448519277854",
        "name": "nana%20-%20c.jpg",
        "path": "file:C:/Python27/YOLO%20+%20GABOR/Data/Source_Images/Training_Images/nana%20-%20c.jpg",
        "size": {
            "width": 1321,
            "height": 1982
        },
        "state": 2,
        "type": 1
    },
    "regions": [
        {
            "id": "v6sLnTjIP",
            "type": "RECTANGLE",
            "tags": [
                "Face"
            ],
            "boundingBox": {
                "height": 662.6932515337423,
                "width": 446.4068965517242,
                "left": 321.23455459770116,
                "top": 161.11349693251535
            },
            "points": [
                {
                    "x": 321.23455459770116,
                    "y": 161.11349693251535
                },
                {
                    "x": 767.6414511494254,
                    "y": 161.11349693251535
                },
                {
                    "x": 767.6414511494254,
                    "y": 823.8067484662577
                },
                {
                    "x": 321.23455459770116,
                    "y": 823.8067484662577
                }
            ]
        }
    ],
    "version": "2.1.0"
}