{
    "asset": {
        "format": "jpg",
        "id": "f3ebec49726f40f095271014ad809f42",
        "name": "puy%20-%20e.jpg",
        "path": "file:C:/Python27/YOLO%20+%20GABOR/Data/Source_Images/Training_Images/puy%20-%20e.jpg",
        "size": {
            "width": 994,
            "height": 1491
        },
        "state": 2,
        "type": 1
    },
    "regions": [
        {
            "id": "j7qngw4N8",
            "type": "RECTANGLE",
            "tags": [
                "Face"
            ],
            "boundingBox": {
                "height": 473.36963190184036,
                "width": 370.1793103448275,
                "left": 340.11652298850566,
                "top": 180.65797546012269
            },
            "points": [
                {
                    "x": 340.11652298850566,
                    "y": 180.65797546012269
                },
                {
                    "x": 710.2958333333331,
                    "y": 180.65797546012269
                },
                {
                    "x": 710.2958333333331,
                    "y": 654.027607361963
                },
                {
                    "x": 340.11652298850566,
                    "y": 654.027607361963
                }
            ]
        }
    ],
    "version": "2.1.0"
}